odoo/addons/product_attribute_value_menu/README.rst
odoo/addons/product_attribute_value_menu/__init__.py
odoo/addons/product_attribute_value_menu/__manifest__.py
odoo/addons/product_attribute_value_menu/i18n/es.po
odoo/addons/product_attribute_value_menu/i18n/it.po
odoo/addons/product_attribute_value_menu/i18n/product_attribute_value_menu.pot
odoo/addons/product_attribute_value_menu/models/__init__.py
odoo/addons/product_attribute_value_menu/models/product_attribute_value.py
odoo/addons/product_attribute_value_menu/readme/CONTRIBUTORS.md
odoo/addons/product_attribute_value_menu/readme/DESCRIPTION.md
odoo/addons/product_attribute_value_menu/readme/USAGE.md
odoo/addons/product_attribute_value_menu/static/description/icon.png
odoo/addons/product_attribute_value_menu/static/description/index.html
odoo/addons/product_attribute_value_menu/views/product_attribute_value_views.xml
odoo/addons/product_attribute_value_menu/views/product_template_attribute_value_views.xml
odoo_addon_product_attribute_value_menu-18.0.1.0.0.4.dist-info/METADATA
odoo_addon_product_attribute_value_menu-18.0.1.0.0.4.dist-info/WHEEL
odoo_addon_product_attribute_value_menu-18.0.1.0.0.4.dist-info/top_level.txt
odoo_addon_product_attribute_value_menu-18.0.1.0.0.4.dist-info/RECORD
